pyexclient/__init__.py
pyexclient/_version.py
pyexclient/workbench.py
pyexclient-1.0.6.dist-info/LICENSE
pyexclient-1.0.6.dist-info/METADATA
pyexclient-1.0.6.dist-info/WHEEL
pyexclient-1.0.6.dist-info/top_level.txt
pyexclient-1.0.6.dist-info/RECORD
