Metadata-Version: 2.1
Name: pyexclient
Version: 1.0.6
Summary: Expel Workbench Client
Home-page: https://github.com/expel-io/pyexclient
Author: Expel Inc.
License: BSD
Requires-Python: >=3.9
License-File: LICENSE
Requires-Dist: requests
